__init__.py
tests/__init__.py
tests/test_data/__init__.py
tests/test_data/test_make_dataset.py
tests/test_data/test_utils.py
tests/test_models/__init__.py
tests/test_models/test_models.py
tests/test_models/test_predict_model.py
tests/test_models/test_train_model.py
tests/test_models/test_utils.py
polony_counting-0.3.0.dist-info/LICENSE
polony_counting-0.3.0.dist-info/METADATA
polony_counting-0.3.0.dist-info/WHEEL
polony_counting-0.3.0.dist-info/RECORD
