Metadata-Version: 2.1
Name: polony-counting
Version: 0.3.0
Summary: 
Home-page: https://github.com/kirill-push/polony-counting
License: MIT
Author: Kirill Pushkarev
Author-email: kirillpush@gmail.com
Requires-Python: >=3.10,<4.0
Classifier: License :: OSI Approved :: MIT License
Classifier: Programming Language :: Python :: 3
Classifier: Programming Language :: Python :: 3.10
Classifier: Programming Language :: Python :: 3.11
Requires-Dist: Pillow (>=9.5.0,<10.0.0)
Requires-Dist: argparse (>=1.4.0,<2.0.0)
Requires-Dist: gdown (>=4.7.1,<5.0.0)
Requires-Dist: h5py (>=3.9.0,<4.0.0)
Requires-Dist: matplotlib (>=3.7.0,<4.0.0)
Requires-Dist: numpy (>=1.23.0,<2.0.0)
Requires-Dist: opencv-python-headless (>=4.8.0,<5.0.0)
Requires-Dist: pyyaml (>=6.0.1,<7.0.0)
Requires-Dist: roifile (>=2023.5.12,<2024.0.0)
Requires-Dist: scipy (>=1.7.0,<2.0.0)
Requires-Dist: tifffile (>=2023.9.26,<2024.0.0)
Requires-Dist: torch (>=2.0.0,!=2.0.1,!=2.1.0)
Requires-Dist: torchvision (>=0.15.0,<0.16.0)
Requires-Dist: types-pyyaml (>=6.0.12.12,<7.0.0.0)
Requires-Dist: wandb (>=0.15.5,<0.16.0)
Project-URL: Repository, https://github.com/kirill-push/polony-counting
